{
  "software_root": "",
  "thermal": {
    "frames": 0,
    "fps": 10,
    "video": "",
    "live_frame": "layer8_ui/artifacts/live_thermal.jpg",
    "output": "",
    "thermal_device": 1,
    "thermal_auto_detect": 1,
    "thermal_detect_max_index": 6,
    "thermal_detect_retry_s": 12,
    "thermal_width": 640,
    "thermal_height": 480,
    "thermal_fps": 30,
    "panel_w": 640,
    "panel_h": 480
  },
  "webcam": {
    "frames": 0,
    "fps": 30,
    "video": "",
    "live_frame": "layer8_ui/artifacts/live_webcam.jpg",
    "output": "",
    "webcam_device": 2,
    "webcam_auto_detect": 1,
    "webcam_detect_max_index": 8,
    "webcam_detect_retry_s": 8,
    "webcam_width": 1920,
    "webcam_height": 1080,
    "metrics_json": "layer8_ui/artifacts/live_threat_metrics.json",
    "active_model_profile_id": "profile_high_resolution",
    "weapon_checkpoint": "layer4_inference/trained_models/gun_detection/gun_prob_best.pt",
    "person_detection_model": "yolov8n.pt",
    "weapon_unsafe_threshold": 0.75,
    "weapon_gun_threshold": 0,
    "weapon_yolo_model": "yolov8n.pt",
    "weapon_conf": 0.22,
    "weapon_image_size": 256,
    "weapon_gun_conf": 0.22,
    "weapon_gun_imgsz": 960,
    "weapon_min_box_px": 28,
    "weapon_gun_min_box_px": 10,
    "weapon_gun_thermal": 1,
    "weapon_no_gun_yolo": 0,
    "weapon_show_yolo_name": 0,
    "weapon_gun_yolo_model": "gun_enhanced_cctv_apr17.pt",
    "weapon_extra_args": "--yolo_classes 0 --gun_roi_pad_px 12",
    "verbose": false
  },
  "mmwave": {
    "frames": 0,
    "mmwave_only": 1,
    "config": "layer1_radar/examples/configs/stable_tracking_indoor2_low_uart.cfg",
    "cli_port": "/dev/ttyUSB0",
    "data_port": "/dev/ttyUSB1",
    "mmwave_show_plot": 1,
    "video": "",
    "live_frame": "layer8_ui/artifacts/live_mmwave.jpg",
    "output": "layer8_ui/artifacts/mmwave_frames.json",
    "no_frame_timeout_s": 30,
    "verbose": false,
    "extra_args": ""
  }
}